jamko_mcp_server/__init__.py
jamko_mcp_server-0.1.0.dist-info/METADATA
jamko_mcp_server-0.1.0.dist-info/WHEEL
jamko_mcp_server-0.1.0.dist-info/entry_points.txt
jamko_mcp_server-0.1.0.dist-info/RECORD
