Metadata-Version: 2.4
Name: jamko-mcp-server
Version: 0.1.0
Summary: Add your description here
Requires-Python: >=3.13.0
Requires-Dist: mcp[cli]>=1.9.3
